LICENSE
README.md
nonebot_plugin_gw2/__init__.py
nonebot_plugin_gw2/api.py
nonebot_plugin_gw2-0.0.4.dist-info/LICENSE
nonebot_plugin_gw2-0.0.4.dist-info/METADATA
nonebot_plugin_gw2-0.0.4.dist-info/WHEEL
nonebot_plugin_gw2-0.0.4.dist-info/RECORD
