Metadata-Version: 2.1
Name: nonebot-plugin-gw2
Version: 0.0.4
Summary: gw2 plugin for NoneBot
Home-page: https://github.com/Agnes4m/nonebot_plugin_gw2
License: MIT
Keywords: game,gw2,nonebot2,plugin
Author: Agnes_Digital
Author-email: Z735803792@163.com
Requires-Python: >=3.8,<4.0
Classifier: License :: OSI Approved :: MIT License
Classifier: Operating System :: OS Independent
Classifier: Programming Language :: Python
Classifier: Programming Language :: Python :: 3
Classifier: Programming Language :: Python :: 3.8
Classifier: Programming Language :: Python :: 3.9
Classifier: Programming Language :: Python :: 3.10
Classifier: Programming Language :: Python :: 3.11
Requires-Dist: asyncio (>=3.4.3)
Requires-Dist: httpx (>=0.22.0)
Requires-Dist: nonebot-adapter-onebot (>=2.1.5)
Requires-Dist: nonebot2 (>=2.0.0,<3.0.0)
Project-URL: Repository, https://github.com/Agnes4m/nonebot_plugin_gw2
